sphinxcontrib_lastupdate-1.1-py2.7-nspkg.pth
sphinxcontrib/lastupdate.py
sphinxcontrib_lastupdate-1.1.dist-info/LICENSE
sphinxcontrib_lastupdate-1.1.dist-info/METADATA
sphinxcontrib_lastupdate-1.1.dist-info/WHEEL
sphinxcontrib_lastupdate-1.1.dist-info/namespace_packages.txt
sphinxcontrib_lastupdate-1.1.dist-info/top_level.txt
sphinxcontrib_lastupdate-1.1.dist-info/RECORD
